Ronan552_Package/__init__.py
Ronan552_Package/hello_word.py
Ronan552_Package-0.0.2.dist-info/LICENSE
Ronan552_Package-0.0.2.dist-info/METADATA
Ronan552_Package-0.0.2.dist-info/WHEEL
Ronan552_Package-0.0.2.dist-info/top_level.txt
Ronan552_Package-0.0.2.dist-info/RECORD
