Metadata-Version: 2.1
Name: Ronan552-Package
Version: 0.0.2
Summary: Basic Hello package
Home-page: UNKNOWN
Author: Ronan White
Author-email: <ronan.white@hotmail.com>
License: UNKNOWN
Keywords: python,Test
Platform: UNKNOWN
Classifier: Development Status :: 1 - Planning
Classifier: Intended Audience :: Developers
Classifier: Programming Language :: Python :: 3
Classifier: Operating System :: Unix
Classifier: Operating System :: MacOS :: MacOS X
Classifier: Operating System :: Microsoft :: Windows
